{
    "updated_at": "2026-03-16 21:17:32",
    "day": 1,
    "date": "2026-03-16",
    "details": {
        "1398201": {
            "fixture_id": 1398201,
            "date": "2026-03-16",
            "time": "21:15",
            "league": "Segunda Liga",
            "country": "Portugal",
            "match": "Torreense - Portimonense",
            "home_team": "Torreense",
            "away_team": "Portimonense",
            "markets": {
                "q1": 1.61,
                "qx": 3.7,
                "q2": 5.1,
                "o25": 1.85,
                "o05ht": 1.36,
                "o15ht": 2.65
            },
            "averages": {
                "home_avg_ft": 2.125,
                "away_avg_ft": 2.875,
                "home_avg_ht": 1.125,
                "away_avg_ht": 1.0,
                "combined_ht_avg": 1.062
            },
            "flags": {
                "fav_quote": 1.61,
                "is_gold_zone": true,
                "home_last_2h_zero": false,
                "away_last_2h_zero": false,
                "drop_diff": 0.0
            },
            "scores": {
                "pt": 4.5,
                "over": 4.4,
                "boost": 4.922,
                "gold": 5.183,
                "max": 5.183
            },
            "tags": [
                "🎯PT",
                "⚽ OVER",
                "🐟O"
            ],
            "home_last_8": [
                {
                    "date": "2026-03-07",
                    "league": "Segunda Liga",
                    "match": "Oliveirense - Torreense",
                    "ht": "0-2",
                    "ft": "0-3",
                    "total_ht_goals": 2,
                    "total_ft_goals": 3
                },
                {
                    "date": "2026-02-28",
                    "league": "Segunda Liga",
                    "match": "Torreense - FC Porto B",
                    "ht": "0-1",
                    "ft": "0-3",
                    "total_ht_goals": 1,
                    "total_ft_goals": 3
                },
                {
                    "date": "2026-02-21",
                    "league": "Segunda Liga",
                    "match": "Torreense - Benfica B",
                    "ht": "1-0",
                    "ft": "1-0",
                    "total_ht_goals": 1,
                    "total_ft_goals": 1
                },
                {
                    "date": "2026-02-15",
                    "league": "Segunda Liga",
                    "match": "Pacos Ferreira - Torreense",
                    "ht": "0-0",
                    "ft": "0-0",
                    "total_ht_goals": 0,
                    "total_ft_goals": 0
                },
                {
                    "date": "2026-02-08",
                    "league": "Segunda Liga",
                    "match": "Torreense - União de Leiria",
                    "ht": "1-1",
                    "ft": "3-1",
                    "total_ht_goals": 2,
                    "total_ft_goals": 4
                },
                {
                    "date": "2026-02-04",
                    "league": "Taça de Portugal",
                    "match": "Fafe - Torreense",
                    "ht": "1-0",
                    "ft": "1-1",
                    "total_ht_goals": 1,
                    "total_ft_goals": 2
                },
                {
                    "date": "2026-01-31",
                    "league": "Segunda Liga",
                    "match": "Academico Viseu - Torreense",
                    "ht": "1-0",
                    "ft": "1-0",
                    "total_ht_goals": 1,
                    "total_ft_goals": 1
                },
                {
                    "date": "2026-01-25",
                    "league": "Segunda Liga",
                    "match": "Torreense - Farense",
                    "ht": "1-0",
                    "ft": "2-1",
                    "total_ht_goals": 1,
                    "total_ft_goals": 3
                }
            ],
            "away_last_8": [
                {
                    "date": "2026-03-07",
                    "league": "Segunda Liga",
                    "match": "Portimonense - Pacos Ferreira",
                    "ht": "2-0",
                    "ft": "2-3",
                    "total_ht_goals": 2,
                    "total_ft_goals": 5
                },
                {
                    "date": "2026-02-28",
                    "league": "Segunda Liga",
                    "match": "União de Leiria - Portimonense",
                    "ht": "0-0",
                    "ft": "1-0",
                    "total_ht_goals": 0,
                    "total_ft_goals": 1
                },
                {
                    "date": "2026-02-22",
                    "league": "Segunda Liga",
                    "match": "Portimonense - Academico Viseu",
                    "ht": "0-0",
                    "ft": "0-1",
                    "total_ht_goals": 0,
                    "total_ft_goals": 1
                },
                {
                    "date": "2026-02-15",
                    "league": "Segunda Liga",
                    "match": "Sporting CP B - Portimonense",
                    "ht": "1-2",
                    "ft": "4-3",
                    "total_ht_goals": 3,
                    "total_ft_goals": 7
                },
                {
                    "date": "2026-02-09",
                    "league": "Segunda Liga",
                    "match": "Portimonense - Benfica B",
                    "ht": "0-0",
                    "ft": "1-1",
                    "total_ht_goals": 0,
                    "total_ft_goals": 2
                },
                {
                    "date": "2026-01-31",
                    "league": "Segunda Liga",
                    "match": "Vizela - Portimonense",
                    "ht": "1-0",
                    "ft": "1-1",
                    "total_ht_goals": 1,
                    "total_ft_goals": 2
                },
                {
                    "date": "2026-01-25",
                    "league": "Segunda Liga",
                    "match": "Portimonense - Feirense",
                    "ht": "0-0",
                    "ft": "0-1",
                    "total_ht_goals": 0,
                    "total_ft_goals": 1
                },
                {
                    "date": "2026-01-21",
                    "league": "Friendlies Clubs",
                    "match": "Portimonense - FC Dallas",
                    "ht": "0-2",
                    "ft": "0-4",
                    "total_ht_goals": 2,
                    "total_ft_goals": 4
                }
            ]
        },
        "1505402": {
            "fixture_id": 1505402,
            "date": "2026-03-16",
            "time": "22:00",
            "league": "Primera División",
            "country": "Chile",
            "match": "Union La Calera - O'Higgins",
            "home_team": "Union La Calera",
            "away_team": "O'Higgins",
            "markets": {
                "q1": 2.62,
                "qx": 3.1,
                "q2": 2.62,
                "o25": 2.2,
                "o05ht": 1.42,
                "o15ht": 2.9
            },
            "averages": {
                "home_avg_ft": 2.125,
                "away_avg_ft": 2.0,
                "home_avg_ht": 1.125,
                "away_avg_ht": 1.0,
                "combined_ht_avg": 1.062
            },
            "flags": {
                "fav_quote": 2.62,
                "is_gold_zone": false,
                "home_last_2h_zero": false,
                "away_last_2h_zero": false,
                "drop_diff": 0.0
            },
            "scores": {
                "pt": 3.6,
                "over": 4.8,
                "boost": 4.222,
                "gold": 3.667,
                "max": 4.8
            },
            "tags": [
                "⚽ OVER",
                "🐟G"
            ],
            "home_last_8": [
                {
                    "date": "2026-03-06",
                    "league": "Primera División",
                    "match": "D. La Serena - Union La Calera",
                    "ht": "2-0",
                    "ft": "3-0",
                    "total_ht_goals": 2,
                    "total_ft_goals": 3
                },
                {
                    "date": "2026-02-27",
                    "league": "Primera División",
                    "match": "Union La Calera - A. Italiano",
                    "ht": "1-0",
                    "ft": "3-0",
                    "total_ht_goals": 1,
                    "total_ft_goals": 3
                },
                {
                    "date": "2026-02-20",
                    "league": "Primera División",
                    "match": "Union La Calera - Nublense",
                    "ht": "0-0",
                    "ft": "0-1",
                    "total_ht_goals": 0,
                    "total_ft_goals": 1
                },
                {
                    "date": "2026-02-15",
                    "league": "Primera División",
                    "match": "Colo Colo - Union La Calera",
                    "ht": "0-0",
                    "ft": "1-0",
                    "total_ht_goals": 0,
                    "total_ft_goals": 1
                },
                {
                    "date": "2026-02-09",
                    "league": "Primera División",
                    "match": "Union La Calera - Cobresal",
                    "ht": "3-1",
                    "ft": "3-1",
                    "total_ht_goals": 4,
                    "total_ft_goals": 4
                },
                {
                    "date": "2026-02-02",
                    "league": "Primera División",
                    "match": "Everton de Vina - Union La Calera",
                    "ht": "0-1",
                    "ft": "0-1",
                    "total_ht_goals": 1,
                    "total_ft_goals": 1
                },
                {
                    "date": "2025-12-06",
                    "league": "Primera División",
                    "match": "U. Catolica - Union La Calera",
                    "ht": "0-1",
                    "ft": "2-1",
                    "total_ht_goals": 1,
                    "total_ft_goals": 3
                },
                {
                    "date": "2025-11-30",
                    "league": "Primera División",
                    "match": "Union La Calera - Deportes Limache",
                    "ht": "0-0",
                    "ft": "0-1",
                    "total_ht_goals": 0,
                    "total_ft_goals": 1
                }
            ],
            "away_last_8": [
                {
                    "date": "2026-03-12",
                    "league": "CONMEBOL Libertadores",
                    "match": "Deportes Tolima - O'Higgins",
                    "ht": "1-0",
                    "ft": "2-0",
                    "total_ht_goals": 1,
                    "total_ft_goals": 2
                },
                {
                    "date": "2026-03-07",
                    "league": "Primera División",
                    "match": "O'Higgins - U. Catolica",
                    "ht": "1-0",
                    "ft": "1-0",
                    "total_ht_goals": 1,
                    "total_ft_goals": 1
                },
                {
                    "date": "2026-03-05",
                    "league": "CONMEBOL Libertadores",
                    "match": "O'Higgins - Deportes Tolima",
                    "ht": "1-0",
                    "ft": "1-0",
                    "total_ht_goals": 1,
                    "total_ft_goals": 1
                },
                {
                    "date": "2026-02-28",
                    "league": "Primera División",
                    "match": "Palestino - O'Higgins",
                    "ht": "1-1",
                    "ft": "4-2",
                    "total_ht_goals": 2,
                    "total_ft_goals": 6
                },
                {
                    "date": "2026-02-21",
                    "league": "Primera División",
                    "match": "O'Higgins - Colo Colo",
                    "ht": "0-0",
                    "ft": "0-1",
                    "total_ht_goals": 0,
                    "total_ft_goals": 1
                },
                {
                    "date": "2026-02-18",
                    "league": "CONMEBOL Libertadores",
                    "match": "O'Higgins - Bahia",
                    "ht": "1-0",
                    "ft": "1-0",
                    "total_ht_goals": 1,
                    "total_ft_goals": 1
                },
                {
                    "date": "2026-02-14",
                    "league": "Primera División",
                    "match": "Deportes Limache - O'Higgins",
                    "ht": "1-1",
                    "ft": "2-1",
                    "total_ht_goals": 2,
                    "total_ft_goals": 3
                },
                {
                    "date": "2026-02-07",
                    "league": "Primera División",
                    "match": "O'Higgins - D. La Serena",
                    "ht": "0-0",
                    "ft": "1-0",
                    "total_ht_goals": 0,
                    "total_ft_goals": 1
                }
            ]
        },
        "1511908": {
            "fixture_id": 1511908,
            "date": "2026-03-16",
            "time": "22:05",
            "league": "Primera B",
            "country": "Colombia",
            "match": "Envigado - Real Cartagena",
            "home_team": "Envigado",
            "away_team": "Real Cartagena",
            "markets": {
                "q1": 2.1,
                "qx": 3.1,
                "q2": 3.3,
                "o25": 2.2,
                "o05ht": 1.44,
                "o15ht": 3.0
            },
            "averages": {
                "home_avg_ft": 1.875,
                "away_avg_ft": 2.75,
                "home_avg_ht": 0.75,
                "away_avg_ht": 1.625,
                "combined_ht_avg": 1.188
            },
            "flags": {
                "fav_quote": 2.1,
                "is_gold_zone": false,
                "home_last_2h_zero": false,
                "away_last_2h_zero": true,
                "drop_diff": 0.0
            },
            "scores": {
                "pt": 4.3,
                "over": 5.1,
                "boost": 4.982,
                "gold": 4.62,
                "max": 5.1
            },
            "tags": [
                "🎯PT",
                "⚽ OVER",
                "🐟G"
            ],
            "home_last_8": [
                {
                    "date": "2026-03-11",
                    "league": "Primera B",
                    "match": "Leones FC - Envigado",
                    "ht": "0-1",
                    "ft": "0-3",
                    "total_ht_goals": 1,
                    "total_ft_goals": 3
                },
                {
                    "date": "2026-03-05",
                    "league": "Primera B",
                    "match": "Envigado - Popayan",
                    "ht": "1-0",
                    "ft": "1-0",
                    "total_ht_goals": 1,
                    "total_ft_goals": 1
                },
                {
                    "date": "2026-03-01",
                    "league": "Primera B",
                    "match": "Orsomarso - Envigado",
                    "ht": "0-0",
                    "ft": "0-1",
                    "total_ht_goals": 0,
                    "total_ft_goals": 1
                },
                {
                    "date": "2026-02-24",
                    "league": "Primera B",
                    "match": "Envigado - Quindio",
                    "ht": "1-1",
                    "ft": "1-2",
                    "total_ht_goals": 2,
                    "total_ft_goals": 3
                },
                {
                    "date": "2026-02-14",
                    "league": "Primera B",
                    "match": "Internacional Palmira - Envigado",
                    "ht": "0-0",
                    "ft": "2-1",
                    "total_ht_goals": 0,
                    "total_ft_goals": 3
                },
                {
                    "date": "2026-02-09",
                    "league": "Primera B",
                    "match": "Envigado - Tigres FC",
                    "ht": "0-0",
                    "ft": "0-0",
                    "total_ht_goals": 0,
                    "total_ft_goals": 0
                },
                {
                    "date": "2026-01-31",
                    "league": "Primera B",
                    "match": "Envigado - Ind. Yumbo",
                    "ht": "0-0",
                    "ft": "2-0",
                    "total_ht_goals": 0,
                    "total_ft_goals": 2
                },
                {
                    "date": "2026-01-26",
                    "league": "Primera B",
                    "match": "Real Soacha - Envigado",
                    "ht": "0-2",
                    "ft": "0-2",
                    "total_ht_goals": 2,
                    "total_ft_goals": 2
                }
            ],
            "away_last_8": [
                {
                    "date": "2026-03-11",
                    "league": "Primera B",
                    "match": "Real Cartagena - Internacional Palmira",
                    "ht": "2-2",
                    "ft": "2-2",
                    "total_ht_goals": 4,
                    "total_ft_goals": 4
                },
                {
                    "date": "2026-03-06",
                    "league": "Primera B",
                    "match": "Real Cartagena - Orsomarso",
                    "ht": "2-0",
                    "ft": "4-0",
                    "total_ht_goals": 2,
                    "total_ft_goals": 4
                },
                {
                    "date": "2026-03-03",
                    "league": "Primera B",
                    "match": "Tigres FC - Real Cartagena",
                    "ht": "0-0",
                    "ft": "0-0",
                    "total_ht_goals": 0,
                    "total_ft_goals": 0
                },
                {
                    "date": "2026-02-21",
                    "league": "Primera B",
                    "match": "Real Cartagena - Leones FC",
                    "ht": "0-2",
                    "ft": "2-3",
                    "total_ht_goals": 2,
                    "total_ft_goals": 5
                },
                {
                    "date": "2026-02-13",
                    "league": "Primera B",
                    "match": "Real Cartagena - Depor FC",
                    "ht": "3-0",
                    "ft": "4-1",
                    "total_ht_goals": 3,
                    "total_ft_goals": 5
                },
                {
                    "date": "2026-02-09",
                    "league": "Primera B",
                    "match": "Bogota FC - Real Cartagena",
                    "ht": "0-1",
                    "ft": "0-1",
                    "total_ht_goals": 1,
                    "total_ft_goals": 1
                },
                {
                    "date": "2026-02-04",
                    "league": "Primera B",
                    "match": "Ind. Yumbo - Real Cartagena",
                    "ht": "0-0",
                    "ft": "1-1",
                    "total_ht_goals": 0,
                    "total_ft_goals": 2
                },
                {
                    "date": "2026-01-31",
                    "league": "Primera B",
                    "match": "Real Cartagena - Real Soacha",
                    "ht": "1-0",
                    "ft": "1-0",
                    "total_ht_goals": 1,
                    "total_ft_goals": 1
                }
            ]
        },
        "1511909": {
            "fixture_id": 1511909,
            "date": "2026-03-16",
            "time": "23:30",
            "league": "Primera B",
            "country": "Colombia",
            "match": "Barranquilla - Bogota FC",
            "home_team": "Barranquilla",
            "away_team": "Bogota FC",
            "markets": {
                "q1": 2.1,
                "qx": 3.1,
                "q2": 3.25,
                "o25": 2.15,
                "o05ht": 1.44,
                "o15ht": 3.0
            },
            "averages": {
                "home_avg_ft": 2.375,
                "away_avg_ft": 1.75,
                "home_avg_ht": 1.375,
                "away_avg_ht": 0.875,
                "combined_ht_avg": 1.125
            },
            "flags": {
                "fav_quote": 2.1,
                "is_gold_zone": false,
                "home_last_2h_zero": false,
                "away_last_2h_zero": false,
                "drop_diff": 0.0
            },
            "scores": {
                "pt": 3.5,
                "over": 5.1,
                "boost": 4.328,
                "gold": 3.772,
                "max": 5.1
            },
            "tags": [
                "⚽ OVER",
                "🐟G"
            ],
            "home_last_8": [
                {
                    "date": "2026-03-11",
                    "league": "Primera B",
                    "match": "Ind. Yumbo - Barranquilla",
                    "ht": "0-0",
                    "ft": "1-0",
                    "total_ht_goals": 0,
                    "total_ft_goals": 1
                },
                {
                    "date": "2026-03-04",
                    "league": "Primera B",
                    "match": "Barranquilla - Union Magdalena",
                    "ht": "0-2",
                    "ft": "1-3",
                    "total_ht_goals": 2,
                    "total_ft_goals": 4
                },
                {
                    "date": "2026-02-26",
                    "league": "Primera B",
                    "match": "Popayan - Barranquilla",
                    "ht": "0-2",
                    "ft": "0-2",
                    "total_ht_goals": 2,
                    "total_ft_goals": 2
                },
                {
                    "date": "2026-02-21",
                    "league": "Primera B",
                    "match": "Barranquilla - Internacional Palmira",
                    "ht": "0-2",
                    "ft": "0-4",
                    "total_ht_goals": 2,
                    "total_ft_goals": 4
                },
                {
                    "date": "2026-02-17",
                    "league": "Primera B",
                    "match": "Quindio - Barranquilla",
                    "ht": "1-0",
                    "ft": "1-0",
                    "total_ht_goals": 1,
                    "total_ft_goals": 1
                },
                {
                    "date": "2026-02-04",
                    "league": "Primera B",
                    "match": "Barranquilla - Patriotas",
                    "ht": "1-0",
                    "ft": "2-0",
                    "total_ht_goals": 1,
                    "total_ft_goals": 2
                },
                {
                    "date": "2026-01-30",
                    "league": "Primera B",
                    "match": "Depor FC - Barranquilla",
                    "ht": "0-1",
                    "ft": "0-2",
                    "total_ht_goals": 1,
                    "total_ft_goals": 2
                },
                {
                    "date": "2026-01-24",
                    "league": "Primera B",
                    "match": "Barranquilla - Orsomarso",
                    "ht": "1-1",
                    "ft": "1-2",
                    "total_ht_goals": 2,
                    "total_ft_goals": 3
                }
            ],
            "away_last_8": [
                {
                    "date": "2026-03-11",
                    "league": "Primera B",
                    "match": "Bogota FC - Tigres FC",
                    "ht": "0-0",
                    "ft": "0-1",
                    "total_ht_goals": 0,
                    "total_ft_goals": 1
                },
                {
                    "date": "2026-03-04",
                    "league": "Primera B",
                    "match": "Ind. Yumbo - Bogota FC",
                    "ht": "1-0",
                    "ft": "1-1",
                    "total_ht_goals": 1,
                    "total_ft_goals": 2
                },
                {
                    "date": "2026-02-27",
                    "league": "Primera B",
                    "match": "Bogota FC - Depor FC",
                    "ht": "0-0",
                    "ft": "1-0",
                    "total_ht_goals": 0,
                    "total_ft_goals": 1
                },
                {
                    "date": "2026-02-22",
                    "league": "Primera B",
                    "match": "Bogota FC - Popayan",
                    "ht": "1-1",
                    "ft": "2-1",
                    "total_ht_goals": 2,
                    "total_ft_goals": 3
                },
                {
                    "date": "2026-02-14",
                    "league": "Primera B",
                    "match": "Patriotas - Bogota FC",
                    "ht": "0-1",
                    "ft": "0-1",
                    "total_ht_goals": 1,
                    "total_ft_goals": 1
                },
                {
                    "date": "2026-02-09",
                    "league": "Primera B",
                    "match": "Bogota FC - Real Cartagena",
                    "ht": "0-1",
                    "ft": "0-1",
                    "total_ht_goals": 1,
                    "total_ft_goals": 1
                },
                {
                    "date": "2026-02-05",
                    "league": "Primera B",
                    "match": "Leones FC - Bogota FC",
                    "ht": "0-0",
                    "ft": "1-1",
                    "total_ht_goals": 0,
                    "total_ft_goals": 2
                },
                {
                    "date": "2026-01-30",
                    "league": "Primera B",
                    "match": "Bogota FC - Internacional Palmira",
                    "ht": "1-1",
                    "ft": "1-2",
                    "total_ht_goals": 2,
                    "total_ft_goals": 3
                }
            ]
        }
    }
}